{
  "Guid": "d728bc2b-5746-4b82-8cfd-cb8c2d14b6eb",
  "Boards": [
    {
      "NumberOfTileTypes": 3,
      "Layers": [
        {
          "Tiles": [
            {
              "Guid": "ea54d73d-7d62-4e96-9395-cca250ff98d3",
              "Type": 0,
              "Position": {
                "x": -240.0,
                "y": 320.0
              }
            },
            {
              "Guid": "d18b38ab-b072-4bb0-b40d-c53d5c3fe6c6",
              "Type": 0,
              "Position": {
                "x": 240.0,
                "y": 320.0
              }
            }
          ]
        },
        {
          "Tiles": [
            {
              "Guid": "cff0b9e3-1329-4e49-a407-177fe4b586e7",
              "Type": 0,
              "Position": {
                "x": -240.0,
                "y": 240.0
              }
            },
            {
              "Guid": "4388894a-7904-4e5d-93b8-329de2e1a682",
              "Type": 0,
              "Position": {
                "x": 240.0,
                "y": 240.0
              }
            },
            {
              "Guid": "340f3a4a-e9a8-48d2-b857-fc5e515959bc",
              "Type": 0,
              "Position": {
                "x": -300.0,
                "y": -160.0
              }
            },
            {
              "Guid": "7d200c75-7c82-48cd-917b-7f01d55d48e4",
              "Type": 0,
              "Position": {
                "x": 300.0,
                "y": -160.0
              }
            }
          ]
        },
        {
          "Tiles": [
            {
              "Guid": "762f3a4c-1190-470c-813e-4b2a27faa988",
              "Type": 0,
              "Position": {
                "x": -280.0,
                "y": -160.0
              }
            },
            {
              "Guid": "de52298c-d32e-40fc-a93c-3940c3b71f35",
              "Type": 0,
              "Position": {
                "x": 280.0,
                "y": -160.0
              }
            },
            {
              "Guid": "922cc921-180e-4c4e-adb1-c52100d32a40",
              "Type": 0,
              "Position": {
                "x": -240.0,
                "y": 160.0
              }
            },
            {
              "Guid": "b5aa1c17-a923-4ffa-9a9a-c865ef837b7c",
              "Type": 0,
              "Position": {
                "x": 240.0,
                "y": 160.0
              }
            }
          ]
        },
        {
          "Tiles": [
            {
              "Guid": "7ad57268-2a2e-4e56-a158-a3de53817248",
              "Type": 0,
              "Position": {
                "x": -160.0,
                "y": 160.0
              }
            },
            {
              "Guid": "6dde29f7-56fe-443d-853b-ec65d98fff54",
              "Type": 0,
              "Position": {
                "x": 160.0,
                "y": 160.0
              }
            },
            {
              "Guid": "7886344a-fdf1-466d-93b7-1eeff015d9ff",
              "Type": 0,
              "Position": {
                "x": -260.0,
                "y": -160.0
              }
            },
            {
              "Guid": "d09a9a5e-81d9-4351-83e1-2dd5427b3933",
              "Type": 0,
              "Position": {
                "x": 260.0,
                "y": -160.0
              }
            }
          ]
        },
        {
          "Tiles": [
            {
              "Guid": "a866c4ae-f272-416d-a0ab-29883f48596d",
              "Type": 0,
              "Position": {
                "x": -240.0,
                "y": -160.0
              }
            },
            {
              "Guid": "4f713fe9-2c67-43de-b2ae-c1a04d8655ea",
              "Type": 0,
              "Position": {
                "x": 240.0,
                "y": -160.0
              }
            },
            {
              "Guid": "f79d09a8-37bd-4cf1-aaf3-ebf3a1016db4",
              "Type": 0,
              "Position": {
                "x": -80.0,
                "y": 80.0
              }
            },
            {
              "Guid": "abba1b11-0e51-4eda-90d8-7dfd51b98f57",
              "Type": 0,
              "Position": {
                "x": 80.0,
                "y": 80.0
              }
            }
          ]
        }
      ]
    },
    {
      "NumberOfTileTypes": 7,
      "Layers": [
        {
          "Tiles": [
            {
              "Guid": "199979a8-26ba-41ef-85f7-db7f0eaf815f",
              "Type": 0,
              "Position": {
                "x": -320.0,
                "y": 320.0
              }
            },
            {
              "Guid": "4d35b76b-b496-429c-9e36-bda43cbea473",
              "Type": 0,
              "Position": {
                "x": -320.0,
                "y": 80.0
              }
            },
            {
              "Guid": "7933f0b4-eb02-4d88-aead-04bbae8b1499",
              "Type": 0,
              "Position": {
                "x": -320.0,
                "y": -160.0
              }
            },
            {
              "Guid": "60663039-733b-4f40-a45c-4f3e3db2cb7e",
              "Type": 0,
              "Position": {
                "x": 320.0,
                "y": 320.0
              }
            },
            {
              "Guid": "8859dd2d-7964-40e8-be60-4ec470efc905",
              "Type": 0,
              "Position": {
                "x": 320.0,
                "y": 80.0
              }
            },
            {
              "Guid": "3565f759-55c3-471e-b10d-d0f2e4614b15",
              "Type": 0,
              "Position": {
                "x": 320.0,
                "y": -160.0
              }
            },
            {
              "Guid": "5e3cb976-4368-436c-b65e-fd0178df819b",
              "Type": 0,
              "Position": {
                "x": -160.0,
                "y": -400.0
              }
            },
            {
              "Guid": "490eb925-3ff2-46ed-9146-45ff1db49a04",
              "Type": 0,
              "Position": {
                "x": 160.0,
                "y": -400.0
              }
            }
          ]
        },
        {
          "Tiles": [
            {
              "Guid": "020d30d6-d920-4ee2-8522-8509ba684884",
              "Type": 0,
              "Position": {
                "x": -240.0,
                "y": 320.0
              }
            },
            {
              "Guid": "af80ca08-bb44-4c30-944a-03da71d155bc",
              "Type": 0,
              "Position": {
                "x": 240.0,
                "y": 320.0
              }
            },
            {
              "Guid": "53a50280-e066-4689-ab0c-88cb533714ac",
              "Type": 0,
              "Position": {
                "x": 240.0,
                "y": 80.0
              }
            },
            {
              "Guid": "a0a61dbc-1ed6-4e6f-a4ec-88e87c24c6b7",
              "Type": 0,
              "Position": {
                "x": -240.0,
                "y": 80.0
              }
            },
            {
              "Guid": "3a415ea2-7733-4e41-95f8-bf6f6d448f5c",
              "Type": 0,
              "Position": {
                "x": -240.0,
                "y": -160.0
              }
            },
            {
              "Guid": "1bb2ce4d-cad2-452b-9fca-c9fdf2f751ab",
              "Type": 0,
              "Position": {
                "x": 240.0,
                "y": -160.0
              }
            },
            {
              "Guid": "4ae1bce7-e84c-4782-8d5d-61e742994197",
              "Type": 0,
              "Position": {
                "x": -160.0,
                "y": -420.0
              }
            },
            {
              "Guid": "c5b2bc58-0dbb-4317-86b7-7fe6cca765c2",
              "Type": 0,
              "Position": {
                "x": 160.0,
                "y": -420.0
              }
            }
          ]
        },
        {
          "Tiles": [
            {
              "Guid": "e98b5020-cbc9-4ef4-952b-92e0d13c3d79",
              "Type": 0,
              "Position": {
                "x": -160.0,
                "y": 320.0
              }
            },
            {
              "Guid": "4dbefe96-0230-49ef-935e-653d89ae7a1f",
              "Type": 0,
              "Position": {
                "x": 160.0,
                "y": 320.0
              }
            },
            {
              "Guid": "a9d0d7e0-8624-4e3a-8672-708b1fdabc67",
              "Type": 0,
              "Position": {
                "x": -160.0,
                "y": 80.0
              }
            },
            {
              "Guid": "a3e3ea11-fe94-4ece-8447-da5f0607a430",
              "Type": 0,
              "Position": {
                "x": 160.0,
                "y": 80.0
              }
            },
            {
              "Guid": "9f70da98-914e-4c24-bfcf-25ca678f83fa",
              "Type": 0,
              "Position": {
                "x": 160.0,
                "y": -160.0
              }
            },
            {
              "Guid": "00fb2c6a-bb51-459b-a3d2-dc129f6170c1",
              "Type": 0,
              "Position": {
                "x": -160.0,
                "y": -160.0
              }
            },
            {
              "Guid": "257b11ce-5874-4e17-9834-4dd56ce9025f",
              "Type": 0,
              "Position": {
                "x": -160.0,
                "y": -440.0
              }
            },
            {
              "Guid": "fd6d26fa-8224-4282-a913-6ad0babbc332",
              "Type": 0,
              "Position": {
                "x": 160.0,
                "y": -440.0
              }
            }
          ]
        },
        {
          "Tiles": [
            {
              "Guid": "66ea3566-a0a2-49e9-aaa3-3191fcbb8baf",
              "Type": 0,
              "Position": {
                "x": -80.0,
                "y": 320.0
              }
            },
            {
              "Guid": "2ee6af5e-c5ec-4430-9439-4e88c466535d",
              "Type": 0,
              "Position": {
                "x": 80.0,
                "y": 320.0
              }
            },
            {
              "Guid": "f1d212c7-a3b7-4fc2-80fd-d5f8215dcb3c",
              "Type": 0,
              "Position": {
                "x": -80.0,
                "y": 80.0
              }
            },
            {
              "Guid": "41357029-f487-4ae0-b074-a43e3c19c840",
              "Type": 0,
              "Position": {
                "x": 80.0,
                "y": 80.0
              }
            },
            {
              "Guid": "cea9b06e-8b6e-43b2-b9cc-25a84faf35cc",
              "Type": 0,
              "Position": {
                "x": -100.0,
                "y": -160.0
              }
            },
            {
              "Guid": "d05396c1-2857-49d5-b927-3a927bb00157",
              "Type": 0,
              "Position": {
                "x": 60.0,
                "y": -160.0
              }
            },
            {
              "Guid": "fb0476de-aaf5-46eb-8ac6-585c10e3c0f3",
              "Type": 0,
              "Position": {
                "x": -160.0,
                "y": -460.0
              }
            },
            {
              "Guid": "b433c352-cf3b-41ca-9d77-6014fd489ffa",
              "Type": 0,
              "Position": {
                "x": 160.0,
                "y": -460.0
              }
            }
          ]
        },
        {
          "Tiles": [
            {
              "Guid": "85941347-1caa-4d9f-964b-04f256134a36",
              "Type": 0,
              "Position": {
                "x": 0.0,
                "y": 320.0
              }
            },
            {
              "Guid": "7fed36c0-43a4-48e6-8ed7-1d46323df893",
              "Type": 0,
              "Position": {
                "x": 0.0,
                "y": 80.0
              }
            },
            {
              "Guid": "687bb156-a253-4177-9ba2-583aa7c2b49a",
              "Type": 0,
              "Position": {
                "x": 0.0,
                "y": -160.0
              }
            }
          ]
        },
        {
          "Tiles": [
            {
              "Guid": "7c7f899f-4440-4723-a567-a56f127c3a04",
              "Type": 0,
              "Position": {
                "x": 0.0,
                "y": 80.0
              }
            }
          ]
        }
      ]
    }
  ],
  "TileCount": 0,
  "Difficult": 1,
  "Key": 4,
  "TileCountAll": 54,
  "DifficultType": 1
}