{
  "Guid": "1e8ddc08-ff72-4eca-a703-aeb5b8f378ff",
  "Boards": [
    {
      "NumberOfTileTypes": 4,
      "Layers": [
        {
          "Tiles": [
            {
              "Guid": "9bb85600-2471-4e09-aecb-15b1d34f681e",
              "Type": 0,
              "Position": {
                "x": 0.0,
                "y": 320.0
              },
              "IncludeMission": false
            },
            {
              "Guid": "1f0288a1-fc0b-47de-a31e-9d58bc27ab2f",
              "Type": 0,
              "Position": {
                "x": 160.0,
                "y": 160.0
              },
              "IncludeMission": false
            },
            {
              "Guid": "79ea0927-a209-4596-b586-8d0329004766",
              "Type": 0,
              "Position": {
                "x": -160.0,
                "y": 160.0
              },
              "IncludeMission": false
            },
            {
              "Guid": "2453ad19-7837-4ac9-8a1a-c6f3713079aa",
              "Type": 0,
              "Position": {
                "x": 320.0,
                "y": 0.0
              },
              "IncludeMission": false
            },
            {
              "Guid": "89d652f5-3bd5-44bb-b3f2-4d32858f2d1c",
              "Type": 0,
              "Position": {
                "x": -320.0,
                "y": 0.0
              },
              "IncludeMission": false
            },
            {
              "Guid": "ac428d89-4c41-47c2-b63b-45d4a41f8015",
              "Type": 0,
              "Position": {
                "x": -320.0,
                "y": -240.0
              },
              "IncludeMission": false
            },
            {
              "Guid": "609ccb73-44e0-4ce7-8900-ad4b4a942f90",
              "Type": 0,
              "Position": {
                "x": 320.0,
                "y": -240.0
              },
              "IncludeMission": false
            },
            {
              "Guid": "2496423c-0d50-4427-bf0f-12db979c59ad",
              "Type": 0,
              "Position": {
                "x": 0.0,
                "y": -240.0
              },
              "IncludeMission": false
            }
          ]
        },
        {
          "Tiles": [
            {
              "Guid": "d04e3439-4293-48e7-ab7b-73ca07f790d9",
              "Type": 0,
              "Position": {
                "x": 0.0,
                "y": 240.0
              },
              "IncludeMission": false
            },
            {
              "Guid": "f3a82c0a-c24e-4ad8-9d2f-a8dcbd6e04f5",
              "Type": 0,
              "Position": {
                "x": 160.0,
                "y": 80.0
              },
              "IncludeMission": false
            },
            {
              "Guid": "bf803b0e-81c1-4b1e-ac99-0eab183acbec",
              "Type": 0,
              "Position": {
                "x": -160.0,
                "y": 80.0
              },
              "IncludeMission": false
            },
            {
              "Guid": "4ac207a5-87ff-49f5-8d1a-1790ef74322c",
              "Type": 0,
              "Position": {
                "x": -320.0,
                "y": -260.0
              },
              "IncludeMission": false
            },
            {
              "Guid": "292ae104-b32b-4bca-9f20-d781e9431d44",
              "Type": 0,
              "Position": {
                "x": 0.0,
                "y": -260.0
              },
              "IncludeMission": false
            },
            {
              "Guid": "b37ad4bd-11b9-4b3f-a517-85b596f31512",
              "Type": 0,
              "Position": {
                "x": 320.0,
                "y": -260.0
              },
              "IncludeMission": false
            }
          ]
        },
        {
          "Tiles": [
            {
              "Guid": "57d87e99-70f4-4484-9f17-fb04a44c66f2",
              "Type": 0,
              "Position": {
                "x": 0.0,
                "y": 160.0
              },
              "IncludeMission": false
            },
            {
              "Guid": "9235f9ae-5834-451d-a5a3-c0724b75c3ae",
              "Type": 0,
              "Position": {
                "x": 160.0,
                "y": 0.0
              },
              "IncludeMission": false
            },
            {
              "Guid": "98d58dfd-8ab8-4800-b62c-cd884a5c35a9",
              "Type": 0,
              "Position": {
                "x": -160.0,
                "y": 0.0
              },
              "IncludeMission": false
            },
            {
              "Guid": "027548cc-bfc2-4213-8876-5489aca19c25",
              "Type": 0,
              "Position": {
                "x": -320.0,
                "y": -280.0
              },
              "IncludeMission": false
            },
            {
              "Guid": "aed23051-dcec-458f-98ee-55cd8ab6f294",
              "Type": 0,
              "Position": {
                "x": 0.0,
                "y": -280.0
              },
              "IncludeMission": false
            },
            {
              "Guid": "1c54ea3d-d460-4d49-9517-d0249dc205c6",
              "Type": 0,
              "Position": {
                "x": 320.0,
                "y": -280.0
              },
              "IncludeMission": false
            }
          ]
        },
        {
          "Tiles": [
            {
              "Guid": "4091f2b5-b0b3-43a5-baf4-5c2417b65785",
              "Type": 0,
              "Position": {
                "x": 0.0,
                "y": 80.0
              },
              "IncludeMission": false
            },
            {
              "Guid": "daa8ee4f-b4d2-4086-8004-e62c6159e621",
              "Type": 0,
              "Position": {
                "x": -320.0,
                "y": -300.0
              },
              "IncludeMission": false
            },
            {
              "Guid": "7dbc642a-ff12-4d3a-9dde-89951cbfdb09",
              "Type": 0,
              "Position": {
                "x": 0.0,
                "y": -300.0
              },
              "IncludeMission": false
            },
            {
              "Guid": "d30aa537-d2ec-4312-a03b-ff4257679850",
              "Type": 0,
              "Position": {
                "x": 320.0,
                "y": -300.0
              },
              "IncludeMission": false
            }
          ]
        }
      ],
      "Difficult": 1,
      "MissionTileCount": 0,
      "GoldTileIcon": -1
    }
  ],
  "HardMode": false,
  "CountryCode": "us",
  "Key": 132
}