{
  "Guid": "3c2e3dd1-c979-4391-b984-d94bfd51eec4",
  "Boards": [
    {
      "NumberOfTileTypes": 4,
      "Layers": [
        {
          "Tiles": [
            {
              "Guid": "13fe9ac8-a8be-45e8-893e-88cf4fade97a",
              "Type": 0,
              "Position": {
                "x": -240.0,
                "y": 240.0
              }
            },
            {
              "Guid": "191d17ae-da79-40a4-bc9f-3a02ca2da55d",
              "Type": 0,
              "Position": {
                "x": -80.0,
                "y": 240.0
              }
            },
            {
              "Guid": "6f0e6b01-553d-459f-bff8-39d5caf125b3",
              "Type": 0,
              "Position": {
                "x": -160.0,
                "y": 80.0
              }
            },
            {
              "Guid": "87ebeebc-e7f9-4336-a6bf-7836254cc857",
              "Type": 0,
              "Position": {
                "x": -160.0,
                "y": -160.0
              }
            },
            {
              "Guid": "c3935fcb-fb1c-45aa-bf7b-3f8d083189a1",
              "Type": 0,
              "Position": {
                "x": 0.0,
                "y": -160.0
              }
            },
            {
              "Guid": "e73eef38-1e1f-435e-8a0f-eda874204b14",
              "Type": 0,
              "Position": {
                "x": 160.0,
                "y": -160.0
              }
            },
            {
              "Guid": "c2b9ba91-2299-456b-98e5-d3f9a01abc17",
              "Type": 0,
              "Position": {
                "x": 80.0,
                "y": 80.0
              }
            },
            {
              "Guid": "af97a1bd-2b18-4d3c-acc1-5ce17c527e5e",
              "Type": 0,
              "Position": {
                "x": 240.0,
                "y": 80.0
              }
            },
            {
              "Guid": "a30fa0f7-3dea-45e3-b213-f64bea348494",
              "Type": 0,
              "Position": {
                "x": 160.0,
                "y": 240.0
              }
            }
          ]
        },
        {
          "Tiles": [
            {
              "Guid": "6c7ea2df-8bb9-41de-aea4-2b82d1554538",
              "Type": 0,
              "Position": {
                "x": -160.0,
                "y": 160.0
              }
            },
            {
              "Guid": "8e43d3af-c373-4d8c-a556-feb60ffaf00c",
              "Type": 0,
              "Position": {
                "x": 160.0,
                "y": 160.0
              }
            },
            {
              "Guid": "97d66be2-9eda-4f33-8bdf-35f29ebfc902",
              "Type": 0,
              "Position": {
                "x": -160.0,
                "y": -180.0
              }
            },
            {
              "Guid": "b20d28a3-1781-4337-b76e-186f1d92b94a",
              "Type": 0,
              "Position": {
                "x": 0.0,
                "y": -180.0
              }
            },
            {
              "Guid": "7d600a11-cee7-4faa-a4db-e28d794ee26a",
              "Type": 0,
              "Position": {
                "x": 160.0,
                "y": -180.0
              }
            }
          ]
        },
        {
          "Tiles": [
            {
              "Guid": "1b248fa3-a735-4738-8d24-5305b0f44ae4",
              "Type": 0,
              "Position": {
                "x": -160.0,
                "y": -200.0
              }
            },
            {
              "Guid": "ae205748-7dce-4eea-89fd-54a38aa99d3e",
              "Type": 0,
              "Position": {
                "x": 0.0,
                "y": -200.0
              }
            },
            {
              "Guid": "f75f79ad-9dcb-4323-b87d-c5d0022b0257",
              "Type": 0,
              "Position": {
                "x": 160.0,
                "y": -200.0
              }
            }
          ]
        },
        {
          "Tiles": [
            {
              "Guid": "99bc2e93-1fb1-454e-82a4-d06b5c74c066",
              "Type": 0,
              "Position": {
                "x": -160.0,
                "y": -220.0
              }
            },
            {
              "Guid": "0b28ac74-c773-4318-a675-64365f0ead32",
              "Type": 0,
              "Position": {
                "x": 0.0,
                "y": -220.0
              }
            },
            {
              "Guid": "d66d9c6c-39b6-4c74-b858-68786058b992",
              "Type": 0,
              "Position": {
                "x": 160.0,
                "y": -220.0
              }
            }
          ]
        },
        {
          "Tiles": [
            {
              "Guid": "2fc4ea1a-0890-489f-b80c-ac7e3a25f5b8",
              "Type": 0,
              "Position": {
                "x": -160.0,
                "y": -240.0
              }
            },
            {
              "Guid": "4365f53f-df89-4326-9fa3-d8182f8fb941",
              "Type": 0,
              "Position": {
                "x": 0.0,
                "y": -240.0
              }
            },
            {
              "Guid": "55f9d2c4-9b71-458f-a6b5-cb4a99a7d6b1",
              "Type": 0,
              "Position": {
                "x": 160.0,
                "y": -240.0
              }
            }
          ]
        },
        {
          "Tiles": [
            {
              "Guid": "882f642f-f404-4b8d-a8cd-cb9e28d3d028",
              "Type": 0,
              "Position": {
                "x": 0.0,
                "y": -260.0
              }
            }
          ]
        }
      ]
    },
    {
      "NumberOfTileTypes": 8,
      "Layers": [
        {
          "Tiles": [
            {
              "Guid": "7b6e69dd-5d31-431e-bbbc-1dddf9fd96e0",
              "Type": 0,
              "Position": {
                "x": -320.0,
                "y": 480.0
              }
            },
            {
              "Guid": "25224fac-6306-4eaf-9bdc-5dd12fbb365b",
              "Type": 0,
              "Position": {
                "x": 320.0,
                "y": 480.0
              }
            },
            {
              "Guid": "6fe09ff0-d13f-418b-8d1d-5f0a05832e8c",
              "Type": 0,
              "Position": {
                "x": -480.0,
                "y": -320.0
              }
            },
            {
              "Guid": "e0ffcc56-8973-4847-9d86-c09e4a46a65c",
              "Type": 0,
              "Position": {
                "x": 480.0,
                "y": -320.0
              }
            }
          ]
        },
        {
          "Tiles": [
            {
              "Guid": "b84f4c6d-7758-450e-a2a4-729f5b758be8",
              "Type": 0,
              "Position": {
                "x": -400.0,
                "y": 400.0
              }
            },
            {
              "Guid": "853d53cc-fab5-40ed-b807-77511544f29a",
              "Type": 0,
              "Position": {
                "x": -240.0,
                "y": 400.0
              }
            },
            {
              "Guid": "08d49bf8-4e46-48a9-8cdc-82d157097a43",
              "Type": 0,
              "Position": {
                "x": 240.0,
                "y": 400.0
              }
            },
            {
              "Guid": "2758852e-1ed7-41ca-81e4-62625a13a9da",
              "Type": 0,
              "Position": {
                "x": 400.0,
                "y": 400.0
              }
            },
            {
              "Guid": "5fcc2202-db48-45d3-a7bf-c9ba7c934b10",
              "Type": 0,
              "Position": {
                "x": -460.0,
                "y": -340.0
              }
            },
            {
              "Guid": "d6422812-675f-4f13-9e3a-42a568118c94",
              "Type": 0,
              "Position": {
                "x": 460.0,
                "y": -340.0
              }
            }
          ]
        },
        {
          "Tiles": [
            {
              "Guid": "ae96706c-9668-455b-bc02-521a5923ef29",
              "Type": 0,
              "Position": {
                "x": -480.0,
                "y": 320.0
              }
            },
            {
              "Guid": "7da25c87-f156-4b77-85e1-a5d7b1df4d6a",
              "Type": 0,
              "Position": {
                "x": -320.0,
                "y": 320.0
              }
            },
            {
              "Guid": "51128ba3-cea0-4510-a9c3-0324d43f7fbe",
              "Type": 0,
              "Position": {
                "x": -160.0,
                "y": 320.0
              }
            },
            {
              "Guid": "b8754c50-2dc3-421e-a254-fbfac3cef0c2",
              "Type": 0,
              "Position": {
                "x": 160.0,
                "y": 320.0
              }
            },
            {
              "Guid": "d370780c-6edb-4645-a0be-91eca0c95eb1",
              "Type": 0,
              "Position": {
                "x": 320.0,
                "y": 320.0
              }
            },
            {
              "Guid": "058265bb-72c9-4647-8ddd-e3c0b2c74540",
              "Type": 0,
              "Position": {
                "x": 480.0,
                "y": 320.0
              }
            },
            {
              "Guid": "cd5701e9-b424-43bd-938f-25ceefb0a707",
              "Type": 0,
              "Position": {
                "x": -440.0,
                "y": -360.0
              }
            },
            {
              "Guid": "aee9483d-343f-4a7f-949e-442825bb5616",
              "Type": 0,
              "Position": {
                "x": 440.0,
                "y": -360.0
              }
            }
          ]
        },
        {
          "Tiles": [
            {
              "Guid": "430ac31b-ca83-49d0-97a2-35d7e8791d92",
              "Type": 0,
              "Position": {
                "x": 80.0,
                "y": 240.0
              }
            },
            {
              "Guid": "382e9261-1518-463d-9427-77cd8b97df52",
              "Type": 0,
              "Position": {
                "x": -80.0,
                "y": 240.0
              }
            },
            {
              "Guid": "51811950-d734-4ae8-ac1d-adfab61d44f6",
              "Type": 0,
              "Position": {
                "x": -240.0,
                "y": 240.0
              }
            },
            {
              "Guid": "6c0c2800-efa4-4a64-b666-dbeffc0abfef",
              "Type": 0,
              "Position": {
                "x": -400.0,
                "y": 240.0
              }
            },
            {
              "Guid": "e0f1d94e-27e5-472c-8f9a-b46144b5b469",
              "Type": 0,
              "Position": {
                "x": 240.0,
                "y": 240.0
              }
            },
            {
              "Guid": "1b3503d0-418e-4e09-b870-cb9d43541936",
              "Type": 0,
              "Position": {
                "x": 400.0,
                "y": 240.0
              }
            },
            {
              "Guid": "1412cba8-42aa-4bb6-ad61-0df6b1fbf5fb",
              "Type": 0,
              "Position": {
                "x": -420.0,
                "y": -380.0
              }
            },
            {
              "Guid": "64ff2ba5-df27-4295-96fc-430776bfcea3",
              "Type": 0,
              "Position": {
                "x": 420.0,
                "y": -380.0
              }
            }
          ]
        },
        {
          "Tiles": [
            {
              "Guid": "6c7d64a5-fce4-47b3-8700-79b6e631566c",
              "Type": 0,
              "Position": {
                "x": -400.0,
                "y": 160.0
              }
            },
            {
              "Guid": "a25aacbf-7133-4458-9fe9-89d56c1b7f98",
              "Type": 0,
              "Position": {
                "x": -240.0,
                "y": 160.0
              }
            },
            {
              "Guid": "5fd15464-f15b-4a99-849e-68b9a03ad652",
              "Type": 0,
              "Position": {
                "x": -80.0,
                "y": 160.0
              }
            },
            {
              "Guid": "96275f12-e140-4c8d-a698-ab31194f911a",
              "Type": 0,
              "Position": {
                "x": 80.0,
                "y": 160.0
              }
            },
            {
              "Guid": "a1a60c8c-312d-4d86-9d4a-c40b927170c8",
              "Type": 0,
              "Position": {
                "x": 240.0,
                "y": 160.0
              }
            },
            {
              "Guid": "d42a1f6c-6196-4a42-8c2f-ca5be12decb1",
              "Type": 0,
              "Position": {
                "x": 400.0,
                "y": 160.0
              }
            },
            {
              "Guid": "1bf74c65-f3a2-4a78-b00c-7267d58ed035",
              "Type": 0,
              "Position": {
                "x": -400.0,
                "y": -400.0
              }
            },
            {
              "Guid": "9ae6b641-309e-4344-a5c1-dd2617c8ecef",
              "Type": 0,
              "Position": {
                "x": 400.0,
                "y": -400.0
              }
            }
          ]
        },
        {
          "Tiles": [
            {
              "Guid": "23be100a-bc32-4dcb-aec0-fc045f065a50",
              "Type": 0,
              "Position": {
                "x": -400.0,
                "y": 80.0
              }
            },
            {
              "Guid": "52fd8b8b-3375-4856-a77c-8954c7e32bf3",
              "Type": 0,
              "Position": {
                "x": -240.0,
                "y": 80.0
              }
            },
            {
              "Guid": "db48ac2b-afb3-4b1d-b804-38e81cfbbe03",
              "Type": 0,
              "Position": {
                "x": -80.0,
                "y": 80.0
              }
            },
            {
              "Guid": "3fe9a9f2-666f-4e34-855f-5b8b948839d2",
              "Type": 0,
              "Position": {
                "x": 80.0,
                "y": 80.0
              }
            },
            {
              "Guid": "f4516a1c-67d8-49a3-a667-b0838dc6beda",
              "Type": 0,
              "Position": {
                "x": 240.0,
                "y": 80.0
              }
            },
            {
              "Guid": "ec8bda3a-690c-4145-be4f-733f5afe748d",
              "Type": 0,
              "Position": {
                "x": 400.0,
                "y": 80.0
              }
            },
            {
              "Guid": "bcf3320b-3765-40dd-8614-6c8b9ca47b91",
              "Type": 0,
              "Position": {
                "x": -380.0,
                "y": -420.0
              }
            },
            {
              "Guid": "d3abec27-2657-437d-8c17-b601ec12f7b8",
              "Type": 0,
              "Position": {
                "x": 380.0,
                "y": -420.0
              }
            }
          ]
        },
        {
          "Tiles": [
            {
              "Guid": "27778679-6020-4b83-9f20-e929d021c058",
              "Type": 0,
              "Position": {
                "x": 320.0,
                "y": 0.0
              }
            },
            {
              "Guid": "4ecd8470-7b66-47c6-b28a-c1aa30d25164",
              "Type": 0,
              "Position": {
                "x": 160.0,
                "y": 0.0
              }
            },
            {
              "Guid": "ce1c9032-85db-4789-9e11-be5b5e13a16e",
              "Type": 0,
              "Position": {
                "x": 0.0,
                "y": 0.0
              }
            },
            {
              "Guid": "fdb4888b-ff05-45bb-bb13-c7d2d53b9707",
              "Type": 0,
              "Position": {
                "x": -160.0,
                "y": 0.0
              }
            },
            {
              "Guid": "2d3b3d85-9f91-4d16-908e-80bfa533f746",
              "Type": 0,
              "Position": {
                "x": -320.0,
                "y": 0.0
              }
            },
            {
              "Guid": "ab595ecf-ecac-46ba-a3a7-72fd34df0954",
              "Type": 0,
              "Position": {
                "x": -360.0,
                "y": -440.0
              }
            },
            {
              "Guid": "ce890cd0-95c5-422d-bb5f-8a6bd163e530",
              "Type": 0,
              "Position": {
                "x": 360.0,
                "y": -440.0
              }
            }
          ]
        },
        {
          "Tiles": [
            {
              "Guid": "f14f7e0f-5b01-4a6a-b381-259b6b3f2f86",
              "Type": 0,
              "Position": {
                "x": -240.0,
                "y": -80.0
              }
            },
            {
              "Guid": "ca91057f-5e13-47a2-9b45-d3ae4cc744f8",
              "Type": 0,
              "Position": {
                "x": -80.0,
                "y": -80.0
              }
            },
            {
              "Guid": "13a2ed1c-d176-45e3-9c0c-7290bfa220d6",
              "Type": 0,
              "Position": {
                "x": 80.0,
                "y": -80.0
              }
            },
            {
              "Guid": "0e8807f6-1333-4b12-9631-b7bebd89be26",
              "Type": 0,
              "Position": {
                "x": 240.0,
                "y": -80.0
              }
            },
            {
              "Guid": "4aa9cb25-b2fe-4d02-9338-abf4cb6ea8b3",
              "Type": 0,
              "Position": {
                "x": -340.0,
                "y": -460.0
              }
            },
            {
              "Guid": "2f09ff21-4071-4b56-8b5e-c0c89549edb9",
              "Type": 0,
              "Position": {
                "x": 340.0,
                "y": -460.0
              }
            }
          ]
        },
        {
          "Tiles": [
            {
              "Guid": "58cf0e62-a707-412f-833a-1d0a5f8a5190",
              "Type": 0,
              "Position": {
                "x": 160.0,
                "y": -160.0
              }
            },
            {
              "Guid": "f51ff5ba-3e34-472e-b677-ed26685e8d84",
              "Type": 0,
              "Position": {
                "x": 0.0,
                "y": -160.0
              }
            },
            {
              "Guid": "64911fe9-d3b8-4ad4-b945-a55218e45f23",
              "Type": 0,
              "Position": {
                "x": -160.0,
                "y": -160.0
              }
            },
            {
              "Guid": "d32f9707-046c-4eea-a957-b26316f548bd",
              "Type": 0,
              "Position": {
                "x": -320.0,
                "y": -480.0
              }
            },
            {
              "Guid": "fc0ac937-482d-484f-8754-f3362abad18e",
              "Type": 0,
              "Position": {
                "x": 320.0,
                "y": -480.0
              }
            }
          ]
        },
        {
          "Tiles": [
            {
              "Guid": "c6cf261d-e700-4aaf-8741-a7e5dbc88b55",
              "Type": 0,
              "Position": {
                "x": -80.0,
                "y": -240.0
              }
            },
            {
              "Guid": "fb3f2383-587c-480b-b883-d1805b26f39a",
              "Type": 0,
              "Position": {
                "x": 80.0,
                "y": -240.0
              }
            }
          ]
        },
        {
          "Tiles": [
            {
              "Guid": "745b42ef-691d-4be1-ac0d-3d352f2414e8",
              "Type": 0,
              "Position": {
                "x": 0.0,
                "y": -320.0
              }
            }
          ]
        }
      ]
    }
  ],
  "TileCount": 0,
  "Difficult": 2,
  "TileCountAll": 87,
  "DifficultType": 2,
  "Key": 195
}