{
  "Guid": "be277370-6bcc-4e6f-a915-19c6236fa902",
  "Boards": [
    {
      "NumberOfTileTypes": 10,
      "Layers": [
        {
          "Tiles": [
            {
              "Guid": "e75a4d40-097c-4472-8970-5c3fef7b8a71",
              "Type": 0,
              "Position": {
                "x": 0.0,
                "y": 320.0
              },
              "IncludeMission": false
            },
            {
              "Guid": "2ff120b6-511e-43c0-bf03-c6733a0b0e10",
              "Type": 0,
              "Position": {
                "x": 80.0,
                "y": 160.0
              },
              "IncludeMission": false
            },
            {
              "Guid": "d21fbfaf-b08d-482c-b883-ae314617a121",
              "Type": 0,
              "Position": {
                "x": -80.0,
                "y": 160.0
              },
              "IncludeMission": false
            },
            {
              "Guid": "a66a9c93-c813-428f-a823-637ab0dc11e1",
              "Type": 0,
              "Position": {
                "x": -80.0,
                "y": 0.0
              },
              "IncludeMission": false
            },
            {
              "Guid": "557c7de6-4310-418a-b220-2882d07590b0",
              "Type": 0,
              "Position": {
                "x": 80.0,
                "y": 0.0
              },
              "IncludeMission": false
            },
            {
              "Guid": "8d82e704-4d59-4ada-a9c2-e9327c9801ba",
              "Type": 0,
              "Position": {
                "x": 80.0,
                "y": -160.0
              },
              "IncludeMission": false
            },
            {
              "Guid": "0a97f884-8cac-49fd-8e27-f98d3bc3f63a",
              "Type": 0,
              "Position": {
                "x": -80.0,
                "y": -160.0
              },
              "IncludeMission": false
            },
            {
              "Guid": "577a5568-5efd-4b27-96a0-9c93bb382fae",
              "Type": 0,
              "Position": {
                "x": 240.0,
                "y": -160.0
              },
              "IncludeMission": false
            },
            {
              "Guid": "3e30c5dc-4637-47e5-b6dd-16be2f26cbb0",
              "Type": 0,
              "Position": {
                "x": -240.0,
                "y": -160.0
              },
              "IncludeMission": false
            },
            {
              "Guid": "ad4cbfa7-8b0d-4946-b9c7-ffcdb5c688d5",
              "Type": 0,
              "Position": {
                "x": 480.0,
                "y": 0.0
              },
              "IncludeMission": false
            },
            {
              "Guid": "7a4f8bd2-eb14-4dc3-bfd6-0b45da73a1a6",
              "Type": 0,
              "Position": {
                "x": 480.0,
                "y": 160.0
              },
              "IncludeMission": false
            },
            {
              "Guid": "3bcc9411-c131-4a36-bd09-162706fa9957",
              "Type": 0,
              "Position": {
                "x": 480.0,
                "y": 320.0
              },
              "IncludeMission": false
            },
            {
              "Guid": "3abae8ef-4249-4b77-ba2e-17dc45f6b4bf",
              "Type": 0,
              "Position": {
                "x": -480.0,
                "y": 0.0
              },
              "IncludeMission": false
            },
            {
              "Guid": "07f92328-1cdd-42b7-bcb9-a733c73f3dc2",
              "Type": 0,
              "Position": {
                "x": -480.0,
                "y": 160.0
              },
              "IncludeMission": false
            },
            {
              "Guid": "ef24e18e-0223-4d23-b62e-aefadda741e1",
              "Type": 0,
              "Position": {
                "x": -480.0,
                "y": 320.0
              },
              "IncludeMission": false
            },
            {
              "Guid": "af3c5752-814a-46d5-958e-0331bce6bfed",
              "Type": 0,
              "Position": {
                "x": -320.0,
                "y": 0.0
              },
              "IncludeMission": false
            },
            {
              "Guid": "9460f7dc-5cb0-4444-a970-4e4a8ea1e228",
              "Type": 0,
              "Position": {
                "x": 320.0,
                "y": 0.0
              },
              "IncludeMission": false
            },
            {
              "Guid": "ecdb489d-c331-4255-9046-82201cc88c2e",
              "Type": 0,
              "Position": {
                "x": -320.0,
                "y": -400.0
              },
              "IncludeMission": false
            },
            {
              "Guid": "b886e959-6edf-4388-b611-a9843b8d10d3",
              "Type": 0,
              "Position": {
                "x": 320.0,
                "y": -400.0
              },
              "IncludeMission": false
            }
          ]
        },
        {
          "Tiles": [
            {
              "Guid": "8d0ed7e9-d05a-4f20-ab60-d0ce15ab0625",
              "Type": 0,
              "Position": {
                "x": 0.0,
                "y": 240.0
              },
              "IncludeMission": false
            },
            {
              "Guid": "fc022e83-1994-4a36-ac39-68d850c2b006",
              "Type": 0,
              "Position": {
                "x": 0.0,
                "y": 80.0
              },
              "IncludeMission": false
            },
            {
              "Guid": "0b5d1e84-f936-4b7d-ba98-a0691e1902e0",
              "Type": 0,
              "Position": {
                "x": 0.0,
                "y": -80.0
              },
              "IncludeMission": false
            },
            {
              "Guid": "a1a844ed-2111-49bd-8384-1096c2788cf0",
              "Type": 0,
              "Position": {
                "x": 400.0,
                "y": 0.0
              },
              "IncludeMission": false
            },
            {
              "Guid": "471b4cf0-efd2-47c0-8842-231294488cdf",
              "Type": 0,
              "Position": {
                "x": 400.0,
                "y": 160.0
              },
              "IncludeMission": false
            },
            {
              "Guid": "1fd623be-e15f-4cec-bf92-063bc536b2d5",
              "Type": 0,
              "Position": {
                "x": -400.0,
                "y": 0.0
              },
              "IncludeMission": false
            },
            {
              "Guid": "6cb93cc3-66d1-4cad-94ce-c27df854e966",
              "Type": 0,
              "Position": {
                "x": -400.0,
                "y": 160.0
              },
              "IncludeMission": false
            },
            {
              "Guid": "c11bd43f-49c8-4011-a50c-bad58eaa09b7",
              "Type": 0,
              "Position": {
                "x": -160.0,
                "y": 0.0
              },
              "IncludeMission": false
            },
            {
              "Guid": "d430b2e0-1fc8-4df9-ad5d-62516b7bf0df",
              "Type": 0,
              "Position": {
                "x": 160.0,
                "y": 0.0
              },
              "IncludeMission": false
            },
            {
              "Guid": "f9e14956-bad6-46b1-acf1-808de4b16478",
              "Type": 0,
              "Position": {
                "x": -300.0,
                "y": -400.0
              },
              "IncludeMission": false
            },
            {
              "Guid": "62b2fd08-849e-4ca2-9bf9-f7bbceda7ede",
              "Type": 0,
              "Position": {
                "x": 300.0,
                "y": -400.0
              },
              "IncludeMission": false
            }
          ]
        },
        {
          "Tiles": [
            {
              "Guid": "0e4513bb-6195-47cf-9126-80de3f907a75",
              "Type": 0,
              "Position": {
                "x": -80.0,
                "y": -160.0
              },
              "IncludeMission": false
            },
            {
              "Guid": "dde49a5a-5da7-4347-80b0-8a538edc1ade",
              "Type": 0,
              "Position": {
                "x": 80.0,
                "y": -160.0
              },
              "IncludeMission": false
            },
            {
              "Guid": "faa77751-9a79-4488-af2f-a6fd2604fa7e",
              "Type": 0,
              "Position": {
                "x": -320.0,
                "y": 0.0
              },
              "IncludeMission": false
            },
            {
              "Guid": "bf5a6855-ca47-4e0c-9b5e-0f6378cbf7d4",
              "Type": 0,
              "Position": {
                "x": 320.0,
                "y": 0.0
              },
              "IncludeMission": false
            },
            {
              "Guid": "94d3f54b-2985-4f05-ae4d-31352df44559",
              "Type": 0,
              "Position": {
                "x": -280.0,
                "y": -400.0
              },
              "IncludeMission": false
            },
            {
              "Guid": "eb608fd0-fda3-4f78-8201-02f34c74710b",
              "Type": 0,
              "Position": {
                "x": 280.0,
                "y": -400.0
              },
              "IncludeMission": false
            },
            {
              "Guid": "fd332055-22ed-4857-bdf4-6ed0f843e40f",
              "Type": 0,
              "Position": {
                "x": 0.0,
                "y": 160.0
              },
              "IncludeMission": false
            }
          ]
        },
        {
          "Tiles": [
            {
              "Guid": "97552a1c-31aa-4e71-aea3-a2a377a21eb7",
              "Type": 0,
              "Position": {
                "x": 160.0,
                "y": -160.0
              },
              "IncludeMission": false
            },
            {
              "Guid": "b9922539-5a58-40b1-bb21-c70fed74146b",
              "Type": 0,
              "Position": {
                "x": -160.0,
                "y": -160.0
              },
              "IncludeMission": false
            },
            {
              "Guid": "547e181e-9ab8-4a80-9fb3-8936371f626f",
              "Type": 0,
              "Position": {
                "x": -260.0,
                "y": -400.0
              },
              "IncludeMission": false
            },
            {
              "Guid": "1edbcc77-1929-4c94-8a38-087973bf915a",
              "Type": 0,
              "Position": {
                "x": 260.0,
                "y": -400.0
              },
              "IncludeMission": false
            },
            {
              "Guid": "2a6ef7dd-5db6-4bf1-a8c6-e362a387d2e0",
              "Type": 0,
              "Position": {
                "x": 0.0,
                "y": 80.0
              },
              "IncludeMission": false
            }
          ]
        },
        {
          "Tiles": [
            {
              "Guid": "9c0d2ca1-63af-48df-9c53-be864f2438c2",
              "Type": 0,
              "Position": {
                "x": 240.0,
                "y": -160.0
              },
              "IncludeMission": false
            },
            {
              "Guid": "8e5c0734-a92d-42c4-9b66-66d3a92b9f68",
              "Type": 0,
              "Position": {
                "x": -240.0,
                "y": -160.0
              },
              "IncludeMission": false
            },
            {
              "Guid": "f6335b90-252f-4702-8a57-e3a28a76a2a1",
              "Type": 0,
              "Position": {
                "x": -240.0,
                "y": -400.0
              },
              "IncludeMission": false
            },
            {
              "Guid": "8eff0f28-fe9b-4571-a284-32b22572211d",
              "Type": 0,
              "Position": {
                "x": 240.0,
                "y": -400.0
              },
              "IncludeMission": false
            },
            {
              "Guid": "b941f46c-20a5-49ba-b2f1-597563fc390c",
              "Type": 0,
              "Position": {
                "x": 0.0,
                "y": 0.0
              },
              "IncludeMission": false
            }
          ]
        },
        {
          "Tiles": [
            {
              "Guid": "7e97e24c-2c6d-4d5d-8086-242894361e78",
              "Type": 0,
              "Position": {
                "x": 320.0,
                "y": -160.0
              },
              "IncludeMission": false
            },
            {
              "Guid": "2fdb293e-1bbe-4872-855f-2868530107be",
              "Type": 0,
              "Position": {
                "x": -320.0,
                "y": -160.0
              },
              "IncludeMission": false
            },
            {
              "Guid": "48682117-1330-4ad3-ab3e-ac1bd702649c",
              "Type": 0,
              "Position": {
                "x": -220.0,
                "y": -400.0
              },
              "IncludeMission": false
            },
            {
              "Guid": "3e5c6bbd-4dc8-4c85-bf08-906c0cb4bf02",
              "Type": 0,
              "Position": {
                "x": 220.0,
                "y": -400.0
              },
              "IncludeMission": false
            }
          ]
        },
        {
          "Tiles": [
            {
              "Guid": "321e1c48-7bc7-4c5e-a9fb-81bae92baff1",
              "Type": 0,
              "Position": {
                "x": 400.0,
                "y": -160.0
              },
              "IncludeMission": false
            },
            {
              "Guid": "45b1ad41-41be-4abb-b115-7246005c652c",
              "Type": 0,
              "Position": {
                "x": -400.0,
                "y": -160.0
              },
              "IncludeMission": false
            },
            {
              "Guid": "b38bfe1c-abd9-442d-a22e-d9c35479b9dd",
              "Type": 0,
              "Position": {
                "x": -200.0,
                "y": -400.0
              },
              "IncludeMission": false
            },
            {
              "Guid": "259de522-3c00-4838-9cf1-c48ed91e8fb0",
              "Type": 0,
              "Position": {
                "x": 200.0,
                "y": -400.0
              },
              "IncludeMission": false
            }
          ]
        },
        {
          "Tiles": [
            {
              "Guid": "c79c61f7-62fc-4427-b59f-ce95d3e689fc",
              "Type": 0,
              "Position": {
                "x": -180.0,
                "y": -400.0
              },
              "IncludeMission": false
            },
            {
              "Guid": "6a164f66-e854-48bf-9d5e-2121d00187a5",
              "Type": 0,
              "Position": {
                "x": 180.0,
                "y": -400.0
              },
              "IncludeMission": false
            }
          ]
        },
        {
          "Tiles": [
            {
              "Guid": "035a91ec-44a2-433d-b55c-0f4e99be5017",
              "Type": 0,
              "Position": {
                "x": -160.0,
                "y": -400.0
              },
              "IncludeMission": false
            },
            {
              "Guid": "e60e1fb1-0e2e-4571-a8a8-6512f2a1396d",
              "Type": 0,
              "Position": {
                "x": 160.0,
                "y": -400.0
              },
              "IncludeMission": false
            }
          ]
        },
        {
          "Tiles": [
            {
              "Guid": "af9620a2-2609-41d6-9bfd-869ac57c4a56",
              "Type": 0,
              "Position": {
                "x": -140.0,
                "y": -400.0
              },
              "IncludeMission": false
            },
            {
              "Guid": "d003a7f2-e556-4b2b-b4de-7670238330a4",
              "Type": 0,
              "Position": {
                "x": 140.0,
                "y": -400.0
              },
              "IncludeMission": false
            }
          ]
        },
        {
          "Tiles": [
            {
              "Guid": "649ea048-7eed-406e-9ae4-4ca960e00f4f",
              "Type": 0,
              "Position": {
                "x": -120.0,
                "y": -400.0
              },
              "IncludeMission": false
            },
            {
              "Guid": "f9cfc73f-7feb-4b09-a6e1-75b382cb10de",
              "Type": 0,
              "Position": {
                "x": 120.0,
                "y": -400.0
              },
              "IncludeMission": false
            }
          ]
        },
        {
          "Tiles": [
            {
              "Guid": "27f5f297-3d1a-44f3-8985-68516adf71f1",
              "Type": 0,
              "Position": {
                "x": -100.0,
                "y": -400.0
              },
              "IncludeMission": false
            },
            {
              "Guid": "3c7976fa-00e8-4f06-b145-33e4ce7754d1",
              "Type": 0,
              "Position": {
                "x": 100.0,
                "y": -400.0
              },
              "IncludeMission": false
            }
          ]
        },
        {
          "Tiles": [
            {
              "Guid": "27f0aa0f-7933-41de-a2cf-2879c049d239",
              "Type": 0,
              "Position": {
                "x": -80.0,
                "y": -400.0
              },
              "IncludeMission": false
            }
          ]
        }
      ],
      "Difficult": 2,
      "MissionTileCount": 0,
      "GoldTileIcon": -1
    }
  ],
  "HardMode": true,
  "CountryCode": "us",
  "Key": 145
}