{
  "Guid": "688b0a47-9d6d-4edd-8513-92f515d2062d",
  "Boards": [
    {
      "NumberOfTileTypes": 9,
      "Layers": [
        {
          "Tiles": [
            {
              "Guid": "7684ffcb-6493-4779-99c3-92381512da23",
              "Type": 0,
              "Position": {
                "x": 240.0,
                "y": 480.0
              },
              "IncludeMission": false
            },
            {
              "Guid": "28b5e310-7f35-4e5b-9894-61b87bd88e95",
              "Type": 0,
              "Position": {
                "x": -240.0,
                "y": 480.0
              },
              "IncludeMission": false
            },
            {
              "Guid": "bb114bfc-a4ee-4189-a68f-aafa904131d3",
              "Type": 0,
              "Position": {
                "x": -400.0,
                "y": 320.0
              },
              "IncludeMission": false
            },
            {
              "Guid": "4d7f7549-c7b0-4305-bdf5-3022b3bfe531",
              "Type": 0,
              "Position": {
                "x": 400.0,
                "y": 320.0
              },
              "IncludeMission": false
            },
            {
              "Guid": "a288e299-64c8-4c6c-bd0d-0b9979d346e3",
              "Type": 0,
              "Position": {
                "x": -480.0,
                "y": -240.0
              },
              "IncludeMission": false
            },
            {
              "Guid": "a9727321-1744-4628-bdac-dc4e422412f5",
              "Type": 0,
              "Position": {
                "x": 480.0,
                "y": -240.0
              },
              "IncludeMission": false
            },
            {
              "Guid": "81894b70-e47e-452d-a191-21e3d03e506c",
              "Type": 0,
              "Position": {
                "x": -320.0,
                "y": -320.0
              },
              "IncludeMission": false
            },
            {
              "Guid": "0153d822-c236-482a-a62c-fe9679e1b1c2",
              "Type": 0,
              "Position": {
                "x": 320.0,
                "y": -320.0
              },
              "IncludeMission": false
            }
          ]
        },
        {
          "Tiles": [
            {
              "Guid": "560b8079-24fb-4e94-abc9-202c42bac000",
              "Type": 0,
              "Position": {
                "x": -320.0,
                "y": 400.0
              },
              "IncludeMission": false
            },
            {
              "Guid": "26fc60b1-9a07-44c6-ba28-1ce81d79aaa4",
              "Type": 0,
              "Position": {
                "x": -160.0,
                "y": 400.0
              },
              "IncludeMission": false
            },
            {
              "Guid": "b69dd983-7a85-4eb0-b2a5-b886edbd6e2d",
              "Type": 0,
              "Position": {
                "x": 160.0,
                "y": 400.0
              },
              "IncludeMission": false
            },
            {
              "Guid": "6708c637-9061-4a96-b8a6-a59efd2877db",
              "Type": 0,
              "Position": {
                "x": 320.0,
                "y": 400.0
              },
              "IncludeMission": false
            },
            {
              "Guid": "ed5e82ec-f934-4269-b56a-cc636d5b59a6",
              "Type": 0,
              "Position": {
                "x": 480.0,
                "y": 240.0
              },
              "IncludeMission": false
            },
            {
              "Guid": "9a581704-0319-4cb5-b8cb-6f1e61e8361d",
              "Type": 0,
              "Position": {
                "x": 80.0,
                "y": -160.0
              },
              "IncludeMission": false
            },
            {
              "Guid": "8085627f-f631-4acd-9593-691e96244380",
              "Type": 0,
              "Position": {
                "x": -80.0,
                "y": -160.0
              },
              "IncludeMission": false
            },
            {
              "Guid": "f63a347c-05af-4fed-afe1-533049a97adc",
              "Type": 0,
              "Position": {
                "x": -480.0,
                "y": 240.0
              },
              "IncludeMission": false
            },
            {
              "Guid": "bad3328b-58d4-4443-b630-68c53e4e8d89",
              "Type": 0,
              "Position": {
                "x": -480.0,
                "y": -260.0
              },
              "IncludeMission": false
            },
            {
              "Guid": "78ea1c20-7350-42e7-8e09-3eb37888f41d",
              "Type": 0,
              "Position": {
                "x": -320.0,
                "y": -340.0
              },
              "IncludeMission": false
            },
            {
              "Guid": "b482a28a-48ff-440c-ad21-9ea695ec8a26",
              "Type": 0,
              "Position": {
                "x": 320.0,
                "y": -340.0
              },
              "IncludeMission": false
            },
            {
              "Guid": "27fca90f-6ae4-4810-8757-739771908177",
              "Type": 0,
              "Position": {
                "x": 480.0,
                "y": -260.0
              },
              "IncludeMission": false
            }
          ]
        },
        {
          "Tiles": [
            {
              "Guid": "595cada6-784f-4d24-b49f-59f195041b3b",
              "Type": 0,
              "Position": {
                "x": -80.0,
                "y": 320.0
              },
              "IncludeMission": false
            },
            {
              "Guid": "8714df28-d93d-48b3-8c64-00627467d8b1",
              "Type": 0,
              "Position": {
                "x": 80.0,
                "y": 320.0
              },
              "IncludeMission": false
            },
            {
              "Guid": "2a776fdb-5604-46a3-b874-ad2313aa3cfb",
              "Type": 0,
              "Position": {
                "x": 480.0,
                "y": 160.0
              },
              "IncludeMission": false
            },
            {
              "Guid": "09872893-8ae1-4338-8b59-a98d4aef2d67",
              "Type": 0,
              "Position": {
                "x": 160.0,
                "y": -80.0
              },
              "IncludeMission": false
            },
            {
              "Guid": "bae98ca8-9c40-4dc0-a8f5-53ee0fc43e50",
              "Type": 0,
              "Position": {
                "x": -160.0,
                "y": -80.0
              },
              "IncludeMission": false
            },
            {
              "Guid": "88215b42-63d7-418f-9160-b07397ca5963",
              "Type": 0,
              "Position": {
                "x": -480.0,
                "y": 160.0
              },
              "IncludeMission": false
            },
            {
              "Guid": "3626fd29-1f10-4331-846f-ee75355adf9e",
              "Type": 0,
              "Position": {
                "x": -480.0,
                "y": -280.0
              },
              "IncludeMission": false
            },
            {
              "Guid": "96807d4a-885b-4cbd-a8b0-76eed28329c1",
              "Type": 0,
              "Position": {
                "x": -320.0,
                "y": -360.0
              },
              "IncludeMission": false
            },
            {
              "Guid": "87cb990b-9c5b-43b1-b8e7-e3b3911c04eb",
              "Type": 0,
              "Position": {
                "x": 320.0,
                "y": -360.0
              },
              "IncludeMission": false
            },
            {
              "Guid": "86c2d6a1-17d8-4e98-908f-d5a99ac5e611",
              "Type": 0,
              "Position": {
                "x": 480.0,
                "y": -280.0
              },
              "IncludeMission": false
            },
            {
              "Guid": "e9ad4baa-3239-4546-8465-08d3615b6dba",
              "Type": 0,
              "Position": {
                "x": 0.0,
                "y": -240.0
              },
              "IncludeMission": false
            }
          ]
        },
        {
          "Tiles": [
            {
              "Guid": "c17a8944-538a-4538-af07-0a295cc0812b",
              "Type": 0,
              "Position": {
                "x": 0.0,
                "y": 240.0
              },
              "IncludeMission": false
            },
            {
              "Guid": "30333bc2-9976-45c3-8c5d-67c6e8da4319",
              "Type": 0,
              "Position": {
                "x": 400.0,
                "y": 80.0
              },
              "IncludeMission": false
            },
            {
              "Guid": "63710c7e-498b-4784-bfea-1e12227f5912",
              "Type": 0,
              "Position": {
                "x": 240.0,
                "y": 0.0
              },
              "IncludeMission": false
            },
            {
              "Guid": "fbaaa885-e54c-47a3-9cf2-25e738b4248e",
              "Type": 0,
              "Position": {
                "x": -240.0,
                "y": 0.0
              },
              "IncludeMission": false
            },
            {
              "Guid": "55da9f65-6f90-4c09-afaf-7a27c9c286c3",
              "Type": 0,
              "Position": {
                "x": -400.0,
                "y": 80.0
              },
              "IncludeMission": false
            },
            {
              "Guid": "d8e9d249-4797-4888-b8d9-ec3f28dcb766",
              "Type": 0,
              "Position": {
                "x": -480.0,
                "y": -300.0
              },
              "IncludeMission": false
            },
            {
              "Guid": "d07c840b-13e1-42c1-8353-3c7a41356999",
              "Type": 0,
              "Position": {
                "x": -320.0,
                "y": -380.0
              },
              "IncludeMission": false
            },
            {
              "Guid": "f5a2cfc9-b9e0-40a3-b0d5-d5897ca786b5",
              "Type": 0,
              "Position": {
                "x": 320.0,
                "y": -380.0
              },
              "IncludeMission": false
            },
            {
              "Guid": "b24e6108-ae83-43d3-b412-22cd0699c61e",
              "Type": 0,
              "Position": {
                "x": 480.0,
                "y": -300.0
              },
              "IncludeMission": false
            }
          ]
        },
        {
          "Tiles": [
            {
              "Guid": "01e699a0-c9a6-413e-ab88-31655a6b462e",
              "Type": 0,
              "Position": {
                "x": -480.0,
                "y": -320.0
              },
              "IncludeMission": false
            },
            {
              "Guid": "d83a613e-f220-46e5-b573-753d2d001417",
              "Type": 0,
              "Position": {
                "x": -320.0,
                "y": -400.0
              },
              "IncludeMission": false
            },
            {
              "Guid": "90625aac-a735-4f4c-936c-a63d56115b7c",
              "Type": 0,
              "Position": {
                "x": 320.0,
                "y": -400.0
              },
              "IncludeMission": false
            },
            {
              "Guid": "fff6cfbc-9d54-4b7b-ba8d-7d017e63e068",
              "Type": 0,
              "Position": {
                "x": 480.0,
                "y": -320.0
              },
              "IncludeMission": false
            },
            {
              "Guid": "42e0608a-84f9-44a6-b748-f066c90c3e78",
              "Type": 0,
              "Position": {
                "x": 0.0,
                "y": 320.0
              },
              "IncludeMission": false
            }
          ]
        },
        {
          "Tiles": [
            {
              "Guid": "2b78fd24-5b9a-4189-b70a-23a5ae6c4c49",
              "Type": 0,
              "Position": {
                "x": -480.0,
                "y": -340.0
              },
              "IncludeMission": false
            },
            {
              "Guid": "fe7119cc-fc04-417f-8709-b6639034ea0a",
              "Type": 0,
              "Position": {
                "x": -320.0,
                "y": -420.0
              },
              "IncludeMission": false
            },
            {
              "Guid": "fa66ff34-27c4-4722-b8e2-7bd565418a3c",
              "Type": 0,
              "Position": {
                "x": 320.0,
                "y": -420.0
              },
              "IncludeMission": false
            },
            {
              "Guid": "fcfd37fe-3de3-4013-a8d6-d0061012cc8c",
              "Type": 0,
              "Position": {
                "x": 480.0,
                "y": -340.0
              },
              "IncludeMission": false
            }
          ]
        },
        {
          "Tiles": [
            {
              "Guid": "67114cf5-8ee1-42d4-a4f0-5b38249ac283",
              "Type": 0,
              "Position": {
                "x": -480.0,
                "y": -360.0
              },
              "IncludeMission": false
            },
            {
              "Guid": "53bfca0b-e0dd-4929-833c-7403ce535fbf",
              "Type": 0,
              "Position": {
                "x": -320.0,
                "y": -440.0
              },
              "IncludeMission": false
            },
            {
              "Guid": "b14acd59-0d60-4a1a-8e57-ae168a3a7014",
              "Type": 0,
              "Position": {
                "x": 320.0,
                "y": -440.0
              },
              "IncludeMission": false
            },
            {
              "Guid": "0a3c39a2-f46a-4935-a329-7a68656e3437",
              "Type": 0,
              "Position": {
                "x": 480.0,
                "y": -360.0
              },
              "IncludeMission": false
            }
          ]
        },
        {
          "Tiles": [
            {
              "Guid": "d80dc474-e391-4a61-b074-e119468e989e",
              "Type": 0,
              "Position": {
                "x": -480.0,
                "y": -380.0
              },
              "IncludeMission": false
            },
            {
              "Guid": "a5184cb4-d516-4b80-92fc-0e33fa71032f",
              "Type": 0,
              "Position": {
                "x": -320.0,
                "y": -460.0
              },
              "IncludeMission": false
            },
            {
              "Guid": "6298efd4-641a-4b8f-83a6-34905ca22c10",
              "Type": 0,
              "Position": {
                "x": 320.0,
                "y": -460.0
              },
              "IncludeMission": false
            },
            {
              "Guid": "0695bc81-e236-4cf3-95fc-cdefecbda872",
              "Type": 0,
              "Position": {
                "x": 480.0,
                "y": -380.0
              },
              "IncludeMission": false
            }
          ]
        },
        {
          "Tiles": [
            {
              "Guid": "5e0c56ff-f4b0-45ce-8e9d-82ec9deb1b08",
              "Type": 0,
              "Position": {
                "x": -480.0,
                "y": -400.0
              },
              "IncludeMission": false
            },
            {
              "Guid": "035c9ee7-2d6a-495a-aeee-2326c8f6b805",
              "Type": 0,
              "Position": {
                "x": -320.0,
                "y": -480.0
              },
              "IncludeMission": false
            },
            {
              "Guid": "e8f5e730-d8a4-4230-8bf7-126bba0259d8",
              "Type": 0,
              "Position": {
                "x": 320.0,
                "y": -480.0
              },
              "IncludeMission": false
            },
            {
              "Guid": "940371d3-9a9f-4219-af83-c01c30c02e02",
              "Type": 0,
              "Position": {
                "x": 480.0,
                "y": -400.0
              },
              "IncludeMission": false
            }
          ]
        },
        {
          "Tiles": [
            {
              "Guid": "b42fd958-7af1-4f4c-a8fc-6a1cb985e4cc",
              "Type": 0,
              "Position": {
                "x": -480.0,
                "y": -420.0
              },
              "IncludeMission": false
            },
            {
              "Guid": "33d6ff4e-2c5d-4a42-a537-3a98096b0de0",
              "Type": 0,
              "Position": {
                "x": 480.0,
                "y": -420.0
              },
              "IncludeMission": false
            }
          ]
        },
        {
          "Tiles": [
            {
              "Guid": "5e5b9cdb-0596-459c-bb99-bfa2426e8740",
              "Type": 0,
              "Position": {
                "x": -480.0,
                "y": -440.0
              },
              "IncludeMission": false
            },
            {
              "Guid": "64a85d7d-ce67-4d22-bcca-8ddd9afff4d8",
              "Type": 0,
              "Position": {
                "x": 480.0,
                "y": -440.0
              },
              "IncludeMission": false
            }
          ]
        },
        {
          "Tiles": [
            {
              "Guid": "6a307c4e-4fc4-4901-a7c3-c1e6760e56ee",
              "Type": 0,
              "Position": {
                "x": -480.0,
                "y": -460.0
              },
              "IncludeMission": false
            },
            {
              "Guid": "8ca79582-6cdb-4351-8a8d-6490b2b6a049",
              "Type": 0,
              "Position": {
                "x": 480.0,
                "y": -460.0
              },
              "IncludeMission": false
            }
          ]
        },
        {
          "Tiles": [
            {
              "Guid": "5e18fcab-3c6e-4a40-8968-da2c7f825338",
              "Type": 0,
              "Position": {
                "x": -480.0,
                "y": -480.0
              },
              "IncludeMission": false
            },
            {
              "Guid": "18230437-6c0c-47f7-864d-2477f19b038f",
              "Type": 0,
              "Position": {
                "x": 480.0,
                "y": -480.0
              },
              "IncludeMission": false
            }
          ]
        }
      ],
      "Difficult": 1,
      "MissionTileCount": 0,
      "GoldTileIcon": -1
    }
  ],
  "HardMode": false,
  "CountryCode": "default",
  "Key": 531
}